hdf5_reader_service/__init__ copy.py
hdf5_reader_service/__init__.py
hdf5_reader_service/__main__.py
hdf5_reader_service/_version.py
hdf5_reader_service/_version_git.py
hdf5_reader_service/api.py
hdf5_reader_service/app.py
hdf5_reader_service/fork.py
hdf5_reader_service/model.py
hdf5_reader_service/utils.py
hdf5_reader_service/tasks/__init__.py
hdf5_reader_service/tasks/metadata.py
hdf5_reader_service/tasks/search.py
hdf5_reader_service/tasks/shapes.py
hdf5_reader_service/tasks/slice.py
hdf5_reader_service/tasks/tree.py
hdf5_reader_service-0.1.4.dist-info/LICENSE
hdf5_reader_service-0.1.4.dist-info/METADATA
hdf5_reader_service-0.1.4.dist-info/WHEEL
hdf5_reader_service-0.1.4.dist-info/entry_points.txt
hdf5_reader_service-0.1.4.dist-info/top_level.txt
hdf5_reader_service-0.1.4.dist-info/RECORD
