Metadata-Version: 2.1
Name: hdf5-reader-service
Version: 0.1.4
Summary: Microservice for reading HDF5 data and serving it via REST, aimed at performance and concurrency
Author-email: Callum Forrester <callum.forrester@diamond.ac.uk>
License: Apache License
Project-URL: GitHub, https://github.com/DiamondLightSource/hdf5-reader-service
Classifier: Development Status :: 3 - Alpha
Classifier: License :: OSI Approved :: Apache Software License
Classifier: Programming Language :: Python :: 3.9
Classifier: Programming Language :: Python :: 3.10
Classifier: Programming Language :: Python :: 3.11
Requires-Python: >=3.9
License-File: LICENSE
Requires-Dist: h5py
Requires-Dist: fastapi
Requires-Dist: uvicorn
Requires-Dist: orjson
Requires-Dist: click
Provides-Extra: dev
Requires-Dist: black ; extra == 'dev'
Requires-Dist: mypy ; extra == 'dev'
Requires-Dist: flake8-isort ; extra == 'dev'
Requires-Dist: Flake8-pyproject ; extra == 'dev'
Requires-Dist: pipdeptree ; extra == 'dev'
Requires-Dist: pre-commit ; extra == 'dev'
Requires-Dist: pydata-sphinx-theme (>=0.12) ; extra == 'dev'
Requires-Dist: pytest ; extra == 'dev'
Requires-Dist: pytest-cov ; extra == 'dev'
Requires-Dist: sphinx-autobuild ; extra == 'dev'
Requires-Dist: sphinx-copybutton ; extra == 'dev'
Requires-Dist: sphinx-design ; extra == 'dev'
Requires-Dist: tox-direct ; extra == 'dev'
Requires-Dist: types-mock ; extra == 'dev'
Requires-Dist: httpx ; extra == 'dev'
